aquacheck/__init__.py
aquacheck/main.py
EnviroChlor-0.0.0.dist-info/LICENSE
EnviroChlor-0.0.0.dist-info/METADATA
EnviroChlor-0.0.0.dist-info/WHEEL
EnviroChlor-0.0.0.dist-info/top_level.txt
EnviroChlor-0.0.0.dist-info/RECORD
