Metadata-Version: 2.1
Name: EnviroChlor
Version: 0.0.0
Summary: An engineering tool for measurements and analyzes the necessary chlorine level for disinfecting water, depending on measured values for DO, temperature, and NTU.
Home-page: https://github.com/ValdrinBeluli/-EnviroChlor--Water-Disinfection-with-Chlorine-based-on-DO-Temperature-and-NTU-
Author: Valdrin Beluli
Author-email: valdrinengineer@gmail.com
Classifier: Programming Language :: Python :: 3
Classifier: License :: OSI Approved :: MIT License
Classifier: Operating System :: OS Independent
Requires-Python: >=3.6
License-File: LICENSE
Requires-Dist: matplotlib
Requires-Dist: numpy
Requires-Dist: tkinter
